MANIFEST.in
README.md
README.rst
setup.py
bravado_bitjws/__init__.py
bravado_bitjws/client.py
bravado_bitjws/requests_client.py
bravado_bitjws.egg-info/PKG-INFO
bravado_bitjws.egg-info/SOURCES.txt
bravado_bitjws.egg-info/dependency_links.txt
bravado_bitjws.egg-info/requires.txt
bravado_bitjws.egg-info/top_level.txt
test/test_auth.py
test/test_init.py
test/test_roundtrip.py