Metadata-Version: 1.1
Name: bravado-bitjws
Version: 0.1.2.1
Summary: Library for accessing Swagger-enabled API's with bitjws authentication.
Home-page: https://github.com/deginner/bravado-bitjws
Author: Deginner
Author-email: ira@deginner.com
License: BSD
Platform: UNKNOWN
Classifier: License :: OSI Approved :: MIT License
Classifier: Programming Language :: Python :: 2
Classifier: Topic :: Software Development :: Libraries
